AMDV_VIDEO_EDITING/__init__.py
AMDV_VIDEO_EDITING/sticker.py
AMDV_VIDEO_EDITING-1.0.1.dist-info/LICENSE
AMDV_VIDEO_EDITING-1.0.1.dist-info/METADATA
AMDV_VIDEO_EDITING-1.0.1.dist-info/WHEEL
AMDV_VIDEO_EDITING-1.0.1.dist-info/entry_points.txt
AMDV_VIDEO_EDITING-1.0.1.dist-info/top_level.txt
AMDV_VIDEO_EDITING-1.0.1.dist-info/RECORD
